gddPy/__init__.py
gddPy/gdd.py
gddpy-1.0.3.dist-info/LICENSE
gddpy-1.0.3.dist-info/METADATA
gddpy-1.0.3.dist-info/WHEEL
gddpy-1.0.3.dist-info/RECORD
